t/__init__.py
t/__main__.py
t/suncalc.py
myt-0.5.6.dist-info/entry_points.txt
myt-0.5.6.dist-info/LICENSE
myt-0.5.6.dist-info/WHEEL
myt-0.5.6.dist-info/METADATA
myt-0.5.6.dist-info/RECORD
